README.txt
setup.py
RainEagle/EagleClass.py
RainEagle/__init__.py
RainEagle.egg-info/PKG-INFO
RainEagle.egg-info/SOURCES.txt
RainEagle.egg-info/dependency_links.txt
RainEagle.egg-info/top_level.txt
bin/meter_status.py
bin/plot_power.py