Metadata-Version: 1.1
Name: RainEagle
Version: 0.1.8
Summary: Python Class for utilizing the Rainforest Automation Eagle ( RFA-Z109 ) socket API.
Home-page: https://github.com/evilpete/RainEagle
Author: Peter Shipley
Author-email: Peter.Shipley@gmail.com
License: BSD
Download-URL: https://github.com/evilpete/RainEagle/archive/0.1.8.tar.gz
Platform: UNKNOWN
